Metadata-Version: 2.1
Name: pyemotionwheel
Version: 0.1.0
Summary: Python library providing a programmatic interface to an emotion wheel, a simple psychological tool for identifying and articulating emotions.
Home-page: https://github.com/jrosebr1/pyemotionwheel
Author: Adrian Rosebrock
Author-email: your.email@example.com
Project-URL: Documentation, https://github.com/jrosebr1/pyemotionwheel#README
Project-URL: Source, https://github.com/jrosebr1/pyemotionwheel
Project-URL: Tracker, https://github.com/jrosebr1/pyemotionwheel/issues
Keywords: emotion wheel,psychological tool,emotion identification,emotional intelligence,therapeutic tool,education,personal development,emotional articulation,emotional literacy,emotional hierarchy
Classifier: Development Status :: 3 - Alpha
Classifier: Intended Audience :: Developers
Classifier: Intended Audience :: Healthcare Industry
Classifier: Intended Audience :: Education
Classifier: Topic :: Software Development :: Libraries
Classifier: Topic :: Scientific/Engineering :: Artificial Intelligence
Classifier: License :: OSI Approved :: MIT License
Classifier: Programming Language :: Python :: 3
Classifier: Programming Language :: Python :: 3.7
Classifier: Programming Language :: Python :: 3.8
Classifier: Programming Language :: Python :: 3.9
Classifier: Programming Language :: Python :: 3.10
Requires-Python: >=3.7
License-File: LICENSE
